com/softalks/numbers.py
com.softalks.numbers-1.0.1.dist-info/LICENSE.txt
com.softalks.numbers-1.0.1.dist-info/METADATA
com.softalks.numbers-1.0.1.dist-info/WHEEL
com.softalks.numbers-1.0.1.dist-info/top_level.txt
com.softalks.numbers-1.0.1.dist-info/RECORD
