Metadata-Version: 2.1
Name: com.softalks.numbers
Version: 1.0.1
Summary: Writes all the natural numbers to console
Author-email: Santiago Ruiz <hiebra@hotmail.com>
License: MIT License
Project-URL: Homepage, https://github.com/hiebra/101-py
Project-URL: Bug Tracker, https://github.com/hiebra/101-py/issues
Classifier: Programming Language :: Python :: 3
Classifier: License :: OSI Approved :: MIT License
Classifier: Operating System :: OS Independent
Requires-Python: >=3.10.6
License-File: LICENSE.txt
Requires-Dist: com.softalks.sh (<2,>=1)
